riskflow_widgets/__init__.py
riskflow_widgets/_version.py
riskflow_widgets/widgets.py
riskflow_widgets/labextension/package.json
riskflow_widgets/labextension/static/216.d2bd44ed44eb763188f0.js
riskflow_widgets/labextension/static/28e3fcaacae52189201f.gif
riskflow_widgets/labextension/static/382.a5a6c7525aecddaa1413.js
riskflow_widgets/labextension/static/382.a5a6c7525aecddaa1413.js.LICENSE.txt
riskflow_widgets/labextension/static/3a5c5ca760a324913b14.png
riskflow_widgets/labextension/static/411.9acacdb48060df47154a.js
riskflow_widgets/labextension/static/486.ab6262a6357d98589954.js
riskflow_widgets/labextension/static/486.ab6262a6357d98589954.js.LICENSE.txt
riskflow_widgets/labextension/static/568.879f27ccff5a28a13add.js
riskflow_widgets/labextension/static/568.879f27ccff5a28a13add.js.LICENSE.txt
riskflow_widgets/labextension/static/59.b68ae3d41a80931aae56.js
riskflow_widgets/labextension/static/645.6ad150d310c7c5ceadad.js
riskflow_widgets/labextension/static/645.6ad150d310c7c5ceadad.js.LICENSE.txt
riskflow_widgets/labextension/static/646.7c01cdd86313ab8a1551.js
riskflow_widgets/labextension/static/755.d6f3ddde9479cef32974.js
riskflow_widgets/labextension/static/755.d6f3ddde9479cef32974.js.LICENSE.txt
riskflow_widgets/labextension/static/7ca36402b36b300be16d.png
riskflow_widgets/labextension/static/a83492a1563137335ce3.png
riskflow_widgets/labextension/static/remoteEntry.2ae71b8b20b981511d05.js
riskflow_widgets/labextension/static/style.js
riskflow_widgets/labextension/static/third-party-licenses.json
riskflow_widgets/nbextension/106a7abc109fb5e78742.png
riskflow_widgets/nbextension/76ecc79260493a07b6fc.png
riskflow_widgets/nbextension/7b8ef9809145cfec0aa6.png
riskflow_widgets/nbextension/extension.js
riskflow_widgets/nbextension/f3bc149017432b87da2e.gif
riskflow_widgets/nbextension/index.js
riskflow_widgets/nbextension/index.js.LICENSE.txt
riskflow_widgets-0.2.1.data/data/etc/jupyter/nbconfig/notebook.d/riskflow_widgets.json
riskflow_widgets-0.2.1.dist-info/METADATA
riskflow_widgets-0.2.1.dist-info/WHEEL
riskflow_widgets-0.2.1.dist-info/top_level.txt
riskflow_widgets-0.2.1.dist-info/RECORD
